Workbook

Sheet DCF>

Sheet WACC
B6: Weighted Average Cost of Capital
B8: All figures are in INR unless stated otherwise.
B10: Peer Comps
H11: Debt / | I11: Debt / | J11: Levered | K11: Unlevered
B12: Name of the Comp | D12: Country | E12: Total Debt | F12: Total Equity | G12: Tax Rate 1 | H12: Equity | I12: Capital | J12: Beta 2 | K12: Beta 3
B14: Avenue Super. | D14: India | E14: ='Beta - Comps'!F6 -> 710.83 | F14: ='Beta - Comps'!E6 -> 228379.45 | G14: 0.3 | H14: =E14/F14 -> 0.0031124955 | I14: =E14/(E14+F14) -> 0.0031028379 | J14: ='Beta - Regression'!J9 -> 1.2421252 | K14: =J14/(1+(1-G14)*H14) -> 1.2394248
B15: Trent | D15: India | E15: ='Beta - Comps'!F7 -> 4525.96 | F15: ='Beta - Comps'!E7 -> 47567.78 | G15: 0.3 | H15: =E15/F15 -> 0.095147598 | I15: =E15/(E15+F15) -> 0.086881072 | J15: 1.4 | K15: =J15/(1+(1-G15)*H15) -> 1.312578
B16: Vedant Fashions | D16: India | E16: ='Beta - Comps'!F8 -> 248.92 | F16: ='Beta - Comps'!E8 -> 28378.34 | G16: 0.3 | H16: =E16/F16 -> 0.0087714785 | I16: =E16/(E16+F16) -> 0.0086952087 | J16: 1.37 | K16: =J16/(1+(1-G16)*H16) -> 1.3616395
B17: Aditya Bir. Fas. | D17: India | E17: ='Beta - Comps'!F9 -> 4617.57 | F17: ='Beta - Comps'!E9 -> 23395.42 | G17: 0.3 | H17: =E17/F17 -> 0.19737068 | I17: =E17/(E17+F17) -> 0.16483674 | J17: 1.23 | K17: =J17/(1+(1-G17)*H17) -> 1.0806921
B18: Metro Brands | D18: India | E18: ='Beta - Comps'!F10 -> 805.48 | F18: ='Beta - Comps'!E10 -> 23076.59 | G18: 0.3 | H18: =E18/F18 -> 0.034904637 | I18: =E18/(E18+F18) -> 0.033727395 | J18: 1.41 | K18: =J18/(1+(1-G18)*H18) -> 1.3763708
F20: Average | G20: =AVERAGE(G14:G18) -> 0.3 | H20: =AVERAGE(H14:H18) -> 0.067861378 | I20: =AVERAGE(I14:I18) -> 0.059448651 | J20: =AVERAGE(J14:J18) -> 1.330425 | K20: =AVERAGE(K14:K18) -> 1.274141
F21: Median | G21: =AVERAGE(G15:G19) -> 0.3 | H21: =AVERAGE(H15:H19) -> 0.084048599 | I21: =MEDIAN(I14:I18) -> 0.033727395 | J21: =MEDIAN(J14:J18) -> 1.37 | K21: =MEDIAN(K14:K18) -> 1.312578
B24: Cost of Debt | G24: Cost of Equity
B26: Pre - Tax Cost of Debt | C26: Interest/debt | E26: =69/710 -> 0.097183099 | G26: Risk Free Rate | K26: 0.07391
B27: Tax Rate | E27: 0.3 | G27: Equity Risk Premium | K27: =Rm!F11-WACC!K26 -> 0.077582308
B28: Post Tax Cost of Debt | E28: =E26*(1-E27) -> 0.068028169 | G28: Levered Beta 4 | K28: =K37 -> 1.6814624
G29: Cost of Equity | K29: =K26+(K27*K28) -> 0.20436174
B32: Capital Structure | G32: Levered Beta
D34: Current | E34: Target | G34: Comps Median Unlivered Beta | K34: =K21 -> 1.312578
B35: Total Debt | C35: =E14 -> 710.83 | D35: =C35/$C$37 -> 0.0031028379 | E35: =I20 -> 0.059448651 | G35: Target Debt / Equity | K35: =E39 -> 0.063206173
B36: Market Capitalization | C36: =F14 -> 228379.45 | D36: =C36/$C$37 -> 0.99689716 | E36: =E37-E35 -> 0.94055135 | G36: Tax Rate | K36: =E27 -> 0.3
B37: Total Capital | C37: =SUM(C35:C36) -> 229090.28 | D37: =SUM(D35:D36) -> 1 | E37: =D37 -> 1 | G37: Levered Beta | K37: =K34*(1+(1-K35)*K36) -> 1.6814624
B39: Debt / Equity | D39: =D35/D36 -> 0.0031124955 | E39: =E35/E36 -> 0.063206173 | G39: Weighted Average Cost of Capital
B41: Notes: | J41: Total Cost | K41: Total Weight
B42: 1. Tax Rate Considered as Marginal Tax Rate for the country | G42: Debt | J42: =E28 -> 0.068028169 | K42: =E35 -> 0.059448651
B43: 2. Levered beta is based on 5 year monthly data | G43: Equity | J43: =K29 -> 0.20436174 | K43: =E36 -> 0.94055135
B44: 3. Unlevered beta = Levered beta/(1+(1-Tax Rate)*Debt/Equity) | G44: Weighted Average Cost of Capital | K44: =SUMPRODUCT(J42:J43,K42:K43) -> 0.19625689
B45: 4. Unlevered beta = Levered beta*(1+(1-Tax Rate)*Debt/Equity)

Sheet Data>
A1: Da

Sheet Beta - Regression
B5: Regression Beta - 2 Years Weekly
B7: Avenue Supermart Weekly Returns | F7: Nifty Returns | I7: Beta Drifting | L7: Beta 1 | M7: =SLOPE(D11:D114,G11:G114) -> 1.2421252 | N7: (Slope)
L8: Beta 2 | M8: =_xlfn.COVARIANCE.S(D11:D114,G11:G114)/_xlfn.VAR.S(G11:G114) -> 1.2421252 | N8: (Covariance)
B9: Date | C9: Closing Price | D9: Return | F9: Closing Price | G9: Return | I9: Levered Raw Beta | J9: =M10 -> 1.2421252
B10: 44249 | C10: 2994.2 | F10: 14529.2 | I10: Raw Beta Weight | J10: 0.75 | L10: Beta 3 | M10: =M29 -> 1.2421252
B11: 44256 | C11: 3286.1 | D11: =C11/C10-1 -> 0.097488478 | F11: 14938.1 | G11: =F11/F10-1 -> 0.028143325
B12: 44263 | C12: 3129.4 | D12: =C12/C11-1 -> -0.047685706 | F12: 15031 | G12: =F12/F11-1 -> 0.0062189971 | I12: Market Beta | J12: 1 | L12: SUMMARY OUTPUT
B13: 44270 | C13: 2960.3 | D13: =C13/C12-1 -> -0.054035917 | F13: 14744 | G13: =F13/F12-1 -> -0.019093873 | I13: Market Beta Weight | J13: =1-J10 -> 0.25
B14: 44277 | C14: 2855.2 | D14: =C14/C13-1 -> -0.035503158 | F14: 14507.3 | G14: =F14/F13-1 -> -0.016053988 | L14: Regression Statistics
B15: 44284 | C15: 2912.7 | D15: =C15/C14-1 -> 0.020138694 | F15: 14867.3 | G15: =F15/F14-1 -> 0.024815093 | I15: Adjusted Beta | J15: =(J9*J10)+(J12*J13) -> 1.1815939 | L15: Multiple R | M15: 0.51109438
B16: 44291 | C16: 2947.8 | D16: =C16/C15-1 -> 0.012050675 | F16: 14834.8 | G16: =F16/F15-1 -> -0.0021860055 | L16: R Square | M16: 0.26121746
B17: 44298 | C17: 2919.9 | D17: =C17/C16-1 -> -0.0094646855 | F17: 14617.8 | G17: =F17/F16-1 -> -0.014627767 | L17: Adjusted R Square | M17: 0.2539745
B18: 44305 | C18: 2713.7 | D18: =C18/C17-1 -> -0.070618857 | F18: 14341.3 | G18: =F18/F17-1 -> -0.018915295 | L18: Standard Error | M18: 0.04228496
B19: 44312 | C19: 2852.9 | D19: =C19/C18-1 -> 0.05129528 | F19: 14631.1 | G19: =F19/F18-1 -> 0.020207373 | L19: Observations | M19: 104
B20: 44319 | C20: 2895.5 | D20: =C20/C19-1 -> 0.014932174 | F20: 14823.2 | G20: =F20/F19-1 -> 0.013129566
B21: 44326 | C21: 2844.6 | D21: =C21/C20-1 -> -0.017579002 | F21: 14677.8 | G21: =F21/F20-1 -> -0.0098089481 | L21: ANOVA
B22: 44333 | C22: 3034.1 | D22: =C22/C21-1 -> 0.066617451 | F22: 15175.3 | G22: =F22/F21-1 -> 0.033894725 | M22: df | N22: SS | O22: MS | P22: F | Q22: Significance F
B23: 44340 | C23: 3022.1 | D23: =C23/C22-1 -> -0.0039550443 | F23: 15435.7 | G23: =F23/F22-1 -> 0.017159463 | L23: Regression | M23: 1 | N23: 0.064484836 | O23: 0.064484836 | P23: 36.064985 | Q23: 2.9601287e-08
B24: 44347 | C24: 3197 | D24: =C24/C23-1 -> 0.057873664 | F24: 15670.3 | G24: =F24/F23-1 -> 0.015198533 | L24: Residual | M24: 102 | N24: 0.18237782 | O24: 0.0017880178
B25: 44354 | C25: 3175.6 | D25: =C25/C24-1 -> -0.0066937754 | F25: 15799.3 | G25: =F25/F24-1 -> 0.0082321334 | L25: Total | M25: 103 | N25: 0.24686265
B26: 44361 | C26: 3317.7 | D26: =C26/C25-1 -> 0.044747449 | F26: 15683.3 | G26: =F26/F25-1 -> -0.0073420974
B27: 44368 | C27: 3315.4 | D27: =C27/C26-1 -> -0.00069325135 | F27: 15860.3 | G27: =F27/F26-1 -> 0.01128589 | M27: Coefficients | N27: Standard Error | O27: t Stat | P27: P-value | Q27: Lower 95% | R27: Upper 95% | S27: Lower 95.0% | T27: Upper 95.0%
B28: 44375 | C28: 3314.3 | D28: =C28/C27-1 -> -0.000331785 | F28: 15722.2 | G28: =F28/F27-1 -> -0.0087072754 | L28: Intercept | M28: 0.0001068556 | N28: 0.004170824 | O28: 0.025619781 | P28: 0.97961066 | Q28: -0.0081659541 | R28: 0.0083796653 | S28: -0.0081659541 | T28: 0.0083796653
B29: 44382 | C29: 3377.6 | D29: =C29/C28-1 -> 0.019099056 | F29: 15689.8 | G29: =F29/F28-1 -> -0.0020607803 | L29: X Variable 1 | M29: 1.2421252 | N29: 0.20683427 | O29: 6.005413 | P29: 2.9601287e-08 | Q29: 0.83187043 | R29: 1.65238 | S29: 0.83187043 | T29: 1.65238
B30: 44389 | C30: 3349.2 | D30: =C30/C29-1 -> -0.0084083373 | F30: 15923.4 | G30: =F30/F29-1 -> 0.014888654
B31: 44396 | C31: 3413.2 | D31: =C31/C30-1 -> 0.019109041 | F31: 15856 | G31: =F31/F30-1 -> -0.0042327644
B32: 44403 | C32: 3500.8 | D32: =C32/C31-1 -> 0.025665065 | F32: 15763 | G32: =F32/F31-1 -> -0.0058652876
B33: 44410 | C33: 3529.2 | D33: =C33/C32-1 -> 0.0081124314 | F33: 16238.2 | G33: =F33/F32-1 -> 0.030146546
B34: 44417 | C34: 3594.6 | D34: =C34/C33-1 -> 0.018531112 | F34: 16529.1 | G34: =F34/F33-1 -> 0.017914547
B35: 44424 | C35: 3643.1 | D35: =C35/C34-1 -> 0.013492461 | F35: 16450.5 | G35: =F35/F34-1 -> -0.0047552498
B36: 44431 | C36: 3833.1 | D36: =C36/C35-1 -> 0.052153386 | F36: 16705.2 | G36: =F36/F35-1 -> 0.015482812
B37: 44438 | C37: 3938.9 | D37: =C37/C36-1 -> 0.02760168 | F37: 17323.6 | G37: =F37/F36-1 -> 0.037018413
B38: 44445 | C38: 3950.5 | D38: =C38/C37-1 -> 0.0029449846 | F38: 17369.3 | G38: =F38/F37-1 -> 0.0026380198
B39: 44452 | C39: 4239.6 | D39: =C39/C38-1 -> 0.07318061 | F39: 17585.2 | G39: =F39/F38-1 -> 0.012429977
B40: 44459 | C40: 4422.4 | D40: =C40/C39-1 -> 0.043117275 | F40: 17853.2 | G40: =F40/F39-1 -> 0.015240088
B41: 44466 | C41: 4235.6 | D41: =C41/C40-1 -> -0.042239508 | F41: 17532.1 | G41: =F41/F40-1 -> -0.017985571
... B114: 44977 | C114: 3552.9 | D114: =C114/C113-1 -> 0.0022284908 | F114: 17844.6 | G114: =F114/F113-1 -> -0.00555054

Sheet Beta - Comps
B5: S.No. | C5: Name | D5: CMP Rs. | E5: Mar Cap Rs.Cr. | F5: Debt Rs.Cr. | G5: Debt / Eq
B6: 1 | C6: Avenue Super. | D6: 3525.6 | E6: 228379.45 | F6: 710.83 | G6: 0.05
B7: 2 | C7: Trent | D7: 1338.1 | E7: 47567.78 | F7: 4525.96 | G7: 1.9
B8: 3 | C8: Vedant Fashions | D8: 1168.9 | E8: 28378.34 | F8: 248.92 | G8: 0.22
B9: 4 | C9: Aditya Bir. Fas. | D9: 246.6 | E9: 23395.42 | F9: 4617.57 | G9: 1.28
B10: 5 | C10: Metro Brands | D10: 849.25 | E10: 23076.59 | F10: 805.48 | G10: 0.56

Sheet Rm
B6: Return on Markets
B8: Year | C8: Annual
B9: 2000 | C9: -0.1465 | E9: Average Return | F9: =AVERAGE(C9:C34) -> 0.15149231
B10: 2001 | C10: -0.1618 | E10: Dividend Yield | F10: 1.39% 1
B11: 2002 | C11: 0.0325 | E11: Total Market Return | F11: =SUM(F9:F10) -> 0.15149231
B12: 2003 | C12: 0.719
B13: 2004 | C13: 0.1068
B14: 2005 | C14: 0.3634
B15: 2006 | C15: 0.3983
B16: 2007 | C16: 0.5477
B17: 2008 | C17: -0.5179
B18: 2009 | C18: 0.7576
B19: 2010 | C19: 0.1795
B20: 2011 | C20: -0.2462
B21: 2012 | C21: 0.277
B22: 2013 | C22: 0.0676
B23: 2014 | C23: 0.3139
... B34: 2025 | C34: 0.1051
