Workbook

Sheet Comps_Val
B2: Amount in Crores
B3: Comparable Company Valuation
D5: Market Data | J5: Market Data | N5: Valuation
B6: Company | C6: Ticker | D6: Share Price | E6: Shares Outstanding | F6: Equity Value | G6: Net Debt | H6: Enterprise Value | J6: Revenue | K6: EBITDA | L6: Net Income | N6: EV/Revenue | O6: EV/EBITDA | P6: P/E
B9: =Data!C3 -> Sun Pharma.Inds. | C9: SUNPHARMA | D9: =Data!D3 -> 1700.5 | E9: =Data!E3 -> 239.93 | F9: =Data!F3 -> 408000.97 | G9: =Data!I3 -> -6116.52 | H9: =F9+G9 -> 401884.45 | J9: =Data!K3 -> 56809.09 | K9: =Data!L3 -> 17253.13 | L9: =Data!M3 -> 10952.92 | N9: =$H9/J9 -> 7.0742982 | O9: =$H9/K9 -> 23.293422 | P9: =F9/L9 -> 37.250429
B10: =Data!C4 -> Divi's Lab. | C10: DIVISLAB | D10: =Data!D4 -> 6149.5 | E10: =Data!E4 -> 26.55 | F10: =Data!F4 -> 163269.23 | G10: =Data!I4 -> -3625 | H10: =F10+G10 -> 159644.23 | J10: =Data!K4 -> 10314 | K10: =Data!L4 -> 3320 | L10: =Data!M4 -> 2479 | N10: =$H10/J10 -> 15.478401 | O10: =$H10/K10 -> 48.08561 | P10: =F10/L10 -> 65.860922
B11: =Data!C5 -> Torrent Pharma. | C11: TORNTPHARM | D11: =Data!D5 -> 4261.5 | E11: =Data!E5 -> 33.84 | F11: =Data!F5 -> 144209.16 | G11: =Data!I5 -> 2242.54 | H11: =F11+G11 -> 146451.7 | J11: =Data!K5 -> 12742 | K11: =Data!L5 -> 3726.19 | L11: =Data!M5 -> 2272 | N11: =$H11/J11 -> 11.49362 | O11: =$H11/K11 -> 39.303337 | P11: =F11/L11 -> 63.472342
B12: =Data!C6 -> Cipla | C12: CIPLA | D12: =Data!D6 -> 1356.4 | E12: =Data!E6 -> 80.78 | F12: =Data!F6 -> 109569.99 | G12: =Data!I6 -> -332.47 | H12: =F12+G12 -> 109237.52 | J12: =Data!K6 -> 28351.08 | K12: =Data!L6 -> 7820.56 | L12: =Data!M6 -> 4533.37 | N12: =$H12/J12 -> 3.8530286 | O12: =$H12/K12 -> 13.967992 | P12: =F12/L12 -> 24.169656
B13: =Data!C7 -> Dr Reddy's Labs | C13: DRREDDY | D13: =Data!D7 -> 1269.4 | E13: =Data!E7 -> 83.46 | F13: =Data!F7 -> 105944.12 | G13: =Data!I7 -> 3393.8 | H13: =F13+G13 -> 109337.92 | J13: =Data!K7 -> 34682.2 | K13: =Data!L7 -> 9514.9 | L13: =Data!M7 -> 5523 | N13: =$H13/J13 -> 3.152566 | O13: =$H13/K13 -> 11.491232 | P13: =F13/L13 -> 19.182351
B14: =Data!C8 -> Lupin | C14: LUPIN | D14: =Data!D8 -> 2221.5 | E14: =Data!E8 -> 45.7 | F14: =Data!F8 -> 101522.55 | G14: =Data!I8 -> 3074.67 | H14: =F14+G14 -> 104597.22 | J14: =Data!K8 -> 26150.5 | K14: =Data!L8 -> 5433.64 | L14: =Data!M8 -> 4669.18 | N14: =$H14/J14 -> 3.9998172 | O14: =$H14/K14 -> 19.249936 | P14: =F14/L14 -> 21.743122
B15: =Data!C9 -> Zydus Lifesci. | C15: ZYDUSLIFE | D15: =Data!D9 -> 910.45 | E15: =Data!E9 -> 100.62 | F15: =Data!F9 -> 91609.479 | G15: =Data!I9 -> 6679.3 | H15: =F15+G15 -> 98288.779 | J15: =Data!K9 -> 26089.3 | K15: =Data!L9 -> 7293.5 | L15: =Data!M9 -> 5026.2 | N15: =$H15/J15 -> 3.7673981 | O15: =$H15/K15 -> 13.476216 | P15: =F15/L15 -> 18.22639
B16: =Data!C10 -> Mankind Pharma | C16: MANKIND | D16: =Data!D10 -> 2083.3 | E16: =Data!E10 -> 41.28 | F16: =Data!F10 -> 85998.624 | G16: =Data!I10 -> 7814.15 | H16: =F16+G16 -> 93812.774 | J16: =Data!K10 -> 13914.08 | K16: =Data!L10 -> 3247.31 | L16: =Data!M10 -> 1803.33 | N16: =$H16/J16 -> 6.7422908 | O16: =$H16/K16 -> 28.88938 | P16: =F16/L16 -> 47.688789
B17: =Data!C11 -> Aurobindo Pharma | C17: AUROPHARMA | D17: =Data!D11 -> 1184.6 | E17: =Data!E11 -> 58.08 | F17: =Data!F11 -> 68801.568 | G17: =Data!I11 -> -440.99 | H17: =F17+G17 -> 68360.578 | J17: =Data!K11 -> 33181.86 | K17: =Data!L11 -> 7139.42 | L17: =Data!M11 -> 3484.96 | N17: =$H17/J17 -> 2.0601792 | O17: =$H17/K17 -> 9.5750885 | P17: =F17/L17 -> 19.742427
B18: =Data!C12 -> Alkem Lab | C18: ALKEM | D18: =Data!D12 -> 5480.5 | E18: =Data!E12 -> 11.96 | F18: =Data!F12 -> 65546.78 | G18: =Data!I12 -> 792.52 | H18: =F18+G18 -> 66339.3 | J18: =Data!K12 -> 14252.7 | K18: =Data!L12 -> 3001.29 | L18: =Data!M12 -> 2422.44 | N18: =$H18/J18 -> 4.6545076 | O18: =$H18/K18 -> 22.103595 | P18: =F18/L18 -> 27.058164
B20: High | N20: =MAX(N9:N18) -> 15.478401 | O20: =MAX(O9:O18) -> 48.08561 | P20: =MAX(P9:P18) -> 65.860922
B21: 75th Percentile | N21: =QUARTILE(N9:N18,3) -> 6.9912964 | O21: =QUARTILE(O9:O18,3) -> 27.490391 | P21: =QUARTILE(P9:P18,3) -> 45.079199
B22: Average | N22: =AVERAGE(N9:N18) -> 6.2276106 | O22: =AVERAGE(O9:O18) -> 22.943581 | P22: =AVERAGE(P9:P18) -> 34.439459
B23: Median | N23: =MEDIAN(N9:N18) -> 4.3271624 | O23: =MEDIAN(O9:O18) -> 20.676766 | P23: =MEDIAN(P9:P18) -> 25.61391
B24: 25th Percentile | N24: =QUARTILE(N9:N18,1) -> 3.7888057 | O24: =QUARTILE(O9:O18,1) -> 13.59916 | P24: =QUARTILE(P9:P18,1) -> 20.242601
B25: Low | N25: =MIN(N9:N18) -> 2.0601792 | O25: =MIN(O9:O18) -> 9.5750885 | P25: =MIN(P9:P18) -> 18.22639
B27: Sun Pharma Comparable Valuation | N27: EV/Revenue | O27: EV/EBITDA | P27: P/E
B29: Implied Enterprise Value | N29: =N$23*J9 -> 245822.16 | O29: =O$23*K9 -> 356738.92
B30: Net Debt | N30: =$G$9 -> -6116.52 | O30: =$G$9 -> -6116.52 | P30: =$G$9 -> -6116.52
B31: Implied Market Value | N31: =SUM(N29:N30) -> 239705.64 | O31: =SUM(O29:O30) -> 350622.4 | P31: =P23*L9 -> 280547.11
B32: Share Outstanding | N32: =$E$9 -> 239.93 | O32: =$E$9 -> 239.93 | P32: =$E$9 -> 239.93
B33: Implied Value per Share | N33: =N31/N32 -> 999.06488 | O33: =O31/O32 -> 1461.3529 | P33: =P31/P32 -> 1169.2873
B34: Source: Screen.in
N35: =IF(N33>$D$9,"Undervalued","Overvalued") -> Overvalued | O35: =IF(O33>$D$9,"Undervalued","Overvalued") -> Overvalued | P35: =IF(P33>$D$9,"Undervalued","Overvalued") -> Overvalued

Sheet Data
B2: S.No. | C2: Name | D2: CMP Rs. | E2: No. Eq. Shares Cr. | F2: Market Cap | G2: Debt Rs.Cr. | H2: Cash End Rs.Cr. | I2: Net Debt | J2: EV | K2: Sales Rs.Cr. | L2: EBIDT Ann Rs.Cr. | M2: NP 12M Rs.Cr. | N2: Mar Cap Rs.Cr.
B3: 1 | C3: Sun Pharma.Inds. | D3: 1700.5 | E3: 239.93 | F3: =E3*D3 -> 408000.97 | G3: 5215.1 | H3: 11331.62 | I3: =G3-H3 -> -6116.52 | J3: =F3+G3-H3 -> 401884.45 | K3: 56809.09 | L3: 17253.13 | M3: 10952.92 | N3: 408006.91
B4: 2 | C4: Divi's Lab. | D4: 6149.5 | E4: 26.55 | F4: =E4*D4 -> 163269.23 | G4: 90 | H4: 3715 | I4: =G4-H4 -> -3625 | J4: =F4+G4-H4 -> 159644.23 | K4: 10314 | L4: 3320 | M4: 2479 | N4: 163249.9
B5: 3 | C5: Torrent Pharma. | D5: 4261.5 | E5: 33.84 | F5: =E5*D5 -> 144209.16 | G5: 2822 | H5: 579.46 | I5: =G5-H5 -> 2242.54 | J5: =F5+G5-H5 -> 146451.7 | K5: 12742 | L5: 3726.19 | M5: 2272 | N5: 144228.52
B6: 4 | C6: Cipla | D6: 1356.4 | E6: 80.78 | F6: =E6*D6 -> 109569.99 | G6: 467.37 | H6: 799.84 | I6: =G6-H6 -> -332.47 | J6: =F6+G6-H6 -> 109237.52 | K6: 28351.08 | L6: 7820.56 | M6: 4533.37 | N6: 109567.37
B7: 5 | C7: Dr Reddy's Labs | D7: 1269.4 | E7: 83.46 | F7: =E7*D7 -> 105944.12 | G7: 5854 | H7: 2460.2 | I7: =G7-H7 -> 3393.8 | J7: =F7+G7-H7 -> 109337.92 | K7: 34682.2 | L7: 9514.9 | M7: 5523 | N7: 105947.98
B8: 6 | C8: Lupin | D8: 2221.5 | E8: 45.7 | F8: =E8*D8 -> 101522.55 | G8: 6217 | H8: 3142.33 | I8: =G8-H8 -> 3074.67 | J8: =F8+G8-H8 -> 104597.22 | K8: 26150.5 | L8: 5433.64 | M8: 4669.18 | N8: 101532.15
B9: 7 | C9: Zydus Lifesci. | D9: 910.45 | E9: 100.62 | F9: =E9*D9 -> 91609.479 | G9: 9636.1 | H9: 2956.8 | I9: =G9-H9 -> 6679.3 | J9: =F9+G9-H9 -> 98288.779 | K9: 26089.3 | L9: 7293.5 | M9: 5026.2 | N9: 91612.57
B10: 8 | C10: Mankind Pharma | D10: 2083.3 | E10: 41.28 | F10: =E10*D10 -> 85998.624 | G10: 8368.65 | H10: 554.5 | I10: =G10-H10 -> 7814.15 | J10: =F10+G10-H10 -> 93812.774 | K10: 13914.08 | L10: 3247.31 | M10: 1803.33 | N10: 85999.68
B11: 9 | C11: Aurobindo Pharma | D11: 1184.6 | E11: 58.08 | F11: =E11*D11 -> 68801.568 | G11: 7794.5 | H11: 8235.49 | I11: =G11-H11 -> -440.99 | J11: =F11+G11-H11 -> 68360.578 | K11: 33181.86 | L11: 7139.42 | M11: 3484.96 | N11: 68801.76
B12: 10 | C12: Alkem Lab | D12: 5480.5 | E12: 11.96 | F12: =E12*D12 -> 65546.78 | G12: 2355.6 | H12: 1563.08 | I12: =G12-H12 -> 792.52 | J12: =F12+G12-H12 -> 66339.3 | K12: 14252.7 | L12: 3001.29 | M12: 2422.44 | N12: 65527.6
B20: 11 | C20: Biocon | D20: 380.35 | E20: 162.09 | F20: =E20*D20 -> 61650.932 | G20: 16535.5 | H20: 4120.2 | J20: =F20+G20-H20 -> 74066.232 | K20: 16827.4 | L20: 4423.6 | M20: 629.6 | N20: 61651.23
B21: 12 | C21: Glenmark Pharma. | D21: 2030.5 | E21: 28.22 | F21: =E21*D21 -> 57300.71 | G21: 1224.17 | H21: 1705.23 | J21: =F21+G21-H21 -> 56819.65 | K21: 16468.13 | L21: 2465.11 | M21: 1065.01 | N21: 57300.87
B22: 13 | C22: Abbott India | D22: 26290 | E22: 2.12 | F22: =E22*D22 -> 55734.8 | G22: 182.45 | H22: 1627.92 | J22: =F22+G22-H22 -> 54289.33 | K22: 6824.13 | L22: 1970.83 | M22: 1524.13 | N22: 55866.25
B23: 14 | C23: Laurus Labs | D23: 1012.45 | E23: 53.99 | F23: =E23*D23 -> 54662.176 | G23: 2211.76 | H23: 144.21 | J23: =F23+G23-H23 -> 56729.726 | K23: 6721.63 | L23: 1073.33 | M23: 840.82 | N23: 54657.78
B24: 15 | C24: Glaxosmi. Pharma | D24: 2597.3 | E24: 16.94 | F24: =E24*D24 -> 43998.262 | G24: 35.71 | H24: 1403.52 | J24: =F24+G24-H24 -> 42630.452 | K24: 3800.74 | L24: 1255.15 | M24: 1020.99 | N24: 43999.83
B25: 16 | C25: Ipca Labs. | D25: 1495.1 | E25: 25.37 | F25: =E25*D25 -> 37930.687 | G25: 1278.92 | H25: 344.23 | J25: =F25+G25-H25 -> 38865.377 | K25: 9504.54 | L25: 1789.93 | M25: 941.08 | N25: 37931.32
B26: 17 | C26: Ajanta Pharma | D26: 2940.1 | E26: 12.49 | F26: =E26*D26 -> 36721.849 | G26: 245.89 | H26: 176.24 | J26: =F26+G26-H26 -> 36791.499 | K26: 5201.63 | L26: 1348.43 | M26: 1014.56 | N26: 36732.32
B27: 18 | C27: J B Chemicals & | D27: 1978.7 | E27: 16.05 | F27: =E27*D27 -> 31758.135 | G27: 19.23 | H27: 129.45 | J27: =F27+G27-H27 -> 31647.915 | K27: 4193.04 | L27: 1043.12 | M27: 753.78 | N27: 31763.59
B28: 19 | C28: Gland Pharma | D28: 1808.2 | E28: 16.48 | F28: =E28*D28 -> 29799.136 | G28: 302.25 | H28: 2556.21 | J28: =F28+G28-H28 -> 27545.176 | K28: 6112.77 | L28: 1481.33 | M28: 847.18 | N28: 29791.26
B29: 20 | C29: Emcure Pharma | D29: 1470.4 | E29: 18.96 | F29: =E29*D29 -> 27878.784 | G29: 1659.22 | H29: 165.3 | J29: =F29+G29-H29 -> 29372.704 | K29: 8850.09 | L29: 1536.16 | M29: 894.77 | N29: 27874.75
B30: 21 | C30: Pfizer | D30: 5017.2 | E30: 4.57 | F30: =E30*D30 -> 22928.604 | G30: 42.98 | H30: 2800.98 | J30: =F30+G30-H30 -> 20170.604 | K30: 2482.33 | L30: 914.1 | M30: 853.55 | N30: 22952.55
B31: 22 | C31: Wockhardt | D31: 1390.1 | E31: 16.25 | F31: =E31*D31 -> 22589.125 | G31: 2456 | H31: 191 | J31: =F31+G31-H31 -> 24854.125 | K31: 3151 | L31: 455 | M31: -10 | N31: 22588.04
... B39: 30 | C39: Alembic Pharma | D39: 769.85 | E39: 19.66 | F39: =E39*D39 -> 15135.251 | G39: 1488.72 | H39: 90.1 | J39: =F39+G39-H39 -> 16533.871 | K39: 7266.82 | L39: 1047.34 | M39: 625.92 | N39: 15132.41
